MANIFEST.in
README.md
README.rst
README.txt
setup.py
geomagpy.egg-info/PKG-INFO
geomagpy.egg-info/SOURCES.txt
geomagpy.egg-info/dependency_links.txt
geomagpy.egg-info/requires.txt
geomagpy.egg-info/top_level.txt
magpy/__init__.py
magpy/absolutes.py
magpy/database.py
magpy/mpplot.py
magpy/stream.py
magpy/transfer.py
magpy/version.py
magpy/acquisition/STANDARD_KEYS.py
magpy/acquisition/__init__.py
magpy/acquisition/acquisition.py
magpy/acquisition/acquisitionsupport.py
magpy/acquisition/arduinoprotocol.py
magpy/acquisition/bm35protocol.py
magpy/acquisition/callprotocol.py
magpy/acquisition/cobs_ws_protocols.py
magpy/acquisition/csprotocol.py
magpy/acquisition/envprotocol.py
magpy/acquisition/gsm19protocol.py
magpy/acquisition/gsm90protocol.py
magpy/acquisition/gsmp20protocol.py
magpy/acquisition/kernprotocol.py
magpy/acquisition/lemiprotocol.py
magpy/acquisition/owprotocol.py
magpy/acquisition/palmacqprotocol.py
magpy/acquisition/pos1protocol.py
magpy/collector/__init__.py
magpy/collector/collector-marcos.py
magpy/collector/collector-martas.py
magpy/collector/collectormethods.py
magpy/collector/subscribe2client.py
magpy/collector/subscribe2marcos.py
magpy/collector/websocket_server.py
magpy/examples/2015-03-25_08-18-00_A2_WIC.txt
magpy/examples/__init__.py
magpy/examples/example1.cdf
magpy/examples/example2.bin
magpy/examples/example4.txt
magpy/examples/example5.cdf
magpy/gui/__init__.py
magpy/gui/absolutespage.py
magpy/gui/analysispage.py
magpy/gui/developpage.py
magpy/gui/dialogclasses.py
magpy/gui/flagpage.py
magpy/gui/magpy.png
magpy/gui/magpy128.xpm
magpy/gui/magpy_gui.py
magpy/gui/magpy_gui_test.py
magpy/gui/metapage.py
magpy/gui/monitorpage.py
magpy/gui/reportpage.py
magpy/gui/streampage.py
magpy/gui/xmagpy
magpy/gui/xmagpy.py
magpy/gui/xmagpyw
magpy/lib/__init__.py
magpy/lib/format_abs_magpy.py
magpy/lib/format_autodif.py
magpy/lib/format_autodif_fread.py
magpy/lib/format_bdv.py
magpy/lib/format_cr800.py
magpy/lib/format_didd.py
magpy/lib/format_dtu.py
magpy/lib/format_gdas.py
magpy/lib/format_gfz.py
magpy/lib/format_gsm19.py
magpy/lib/format_iaga02.py
magpy/lib/format_imf.py
magpy/lib/format_iono.py
