Metadata-Version: 1.0
Name: geomagpy
Version: 0.4.4
Summary: Geomagnetic analysis tools.
Home-page: http://pypi.python.org/pypi/geomagpy/
Author: R. Leonhardt, R. Bailey, M. Miklavec, J. Fee, H. Schovanec
Author-email: roman.leonhardt@zamg.ac.at
License: LICENSE.txt
Platform: UNKNOWN
